{"FaxYmSnLHNfP6jDNNuHKpQ==":"mbr-2000x1333.jpg","IJpa+H1CgmO4GN6cSLFXmw==":"mbr-2000x1330.jpg","lzBKWfgsFiUj3RGdfJWX/g==":"mbr-1400x933.jpg","KvfJIJ/cYS+WdAVwOtPI7g==":"7910391_orig-1400x1633.png","tGrVG/RSlcLFqMDvuNnz+A==":"mbr-1-2000x1333.jpg","3RShSMibaDfdb4jw1J9ZzA==":"mbr-2-2000x1333.jpg","zsyVVN93F4vyUDIKvpfAYA==":"mbr-3-2000x1333.jpg","I/u0ATyGmjeZx09Cz1NWVg==":"quizmaster_2-1400x1400.jpg","ydm/1YByDy04/NbhyCY6Cw==":"lightbulb-quiz-1400x933.png","A8WDfNi+Seq5IwRFwnir2g==":"mechanical-drafting-technicians-1400x933.jpg","mMywRMJ25llLVenAzNjXbg==":"mbr-4-2000x1333.jpg","1/KBGWHgLfeJKItzxv/ZEQ==":"trzydziesci-procent-wody-w-butelce-rakiety-1400x1050.jpg","DG3uWhVvfiSuKg9kFJCjJQ==":"mbr-2000x1335.jpg","r0Dc4bIPwGiD+azrpJIkWw==":"mbr-5-2000x1333.jpg","/lwT6F+Y5IVUZ0XFScQLLA==":"1-1400x788.jpg"}